{
  "articles": [
    {
      "id": 1,
      "title": "Quay lại TPHCM sau Tết, cô gái \"choáng\" vì tô phở tăng 10.000 đồng",
      "summary": "<a href=\"https://dantri.com.vn/doi-song/quay-lai-tphcm-sau-tet-co-gai-choang-vi-to-pho-tang-10000-dong-20260303212817233.htm\"><img src=\"https://icdn.dantri.com.vn/2026/03/03/z75838640837571b2ef9ba58d89c40e6564f151022f44ajpg-1772546894107.jpg\" /></a>(Dân trí) - Sau Tết, nhiều hàng quán ở TPHCM đồng loạt tăng giá. Khách buộc lòng phải tính toán lại chi tiêu, còn chủ quán cũng đắn đo, khó xử vì... “không tăng không được”."
    },
    {
      "id": 2,
      "title": "Israel thả hơn 5.000 quả bom xuống Iran",
      "summary": "<a href=\"https://dantri.com.vn/the-gioi/israel-tha-hon-5000-qua-bom-xuong-iran-20260305051624955.htm\"><img src=\"https://icdn.dantri.com.vn/2026/03/05/als61ngif-1772662461235.gif\" /></a>(Dân trí) - Quân đội Israel cho biết Không quân nước này đã thả hơn 5.000 quả bom xuống các mục tiêu tại Iran kể từ khi xung đột bắt đầu vào cuối tuần trước."
    },
    {
      "id": 3,
      "title": "Tắc trách khi để nhà dân cheo leo bên mép vực ở Đồng Nai",
      "summary": "<a href=\"https://dantri.com.vn/thoi-su/tac-trach-khi-de-nha-dan-cheo-leo-ben-mep-vuc-o-dong-nai-20260304183609377.htm\"><img src=\"https://icdn.dantri.com.vn/2026/03/04/hacotnenbinhphuocphuoctuan26-edited-1772435927089jpg-1772611925744.jpg\" /></a>(Dân trí) - Theo chuyên gia, đơn vị thi công đường ĐT753 (Đồng Nai) đã xem nhẹ tiêu chí an toàn khi tạo ra vách taluy dựng đứng mà không gia cố hay rào chắn, tiềm ẩn nguy cơ sạt lở và tai nạn cho người dân."
    }
  ]
}